lemberg_ai/__init__.py
lemberg_ai-0.0.0.dist-info/METADATA
lemberg_ai-0.0.0.dist-info/UNLICENSE
lemberg_ai-0.0.0.dist-info/WHEEL
lemberg_ai-0.0.0.dist-info/top_level.txt
lemberg_ai-0.0.0.dist-info/RECORD
