Metadata-Version: 2.1
Name: lemberg-ai
Version: 0.0.0
Summary: Lemberg.AI Software Development Kit (SDK) for Python
Home-page: https://github.com/LembergAI/LembergAI.py
Author: Arto Bendiken
Author-email: arto@lemberg.ai
License: Public Domain
Project-URL: Source, https://github.com/LembergAI/LembergAI.py
Platform: UNKNOWN
Classifier: Development Status :: 2 - Pre-Alpha
Classifier: Environment :: Console
Classifier: Intended Audience :: Developers
Classifier: Intended Audience :: Information Technology
Classifier: License :: Public Domain
Classifier: Natural Language :: English
Classifier: Operating System :: OS Independent
Classifier: Programming Language :: Python :: 3 :: Only
Classifier: Programming Language :: Python :: 3.6
Classifier: Programming Language :: Python :: 3.7
Classifier: Programming Language :: Python :: 3.8
Classifier: Topic :: Software Development :: Libraries
Requires-Python: ~=3.6
Provides-Extra: test
Requires-Dist: pytest ; extra == 'test'
